regfile/dff/d_latch.v
module d_latch(
    input clk, data,
    output q, q_not
);
    wire set_out, reset_out, data_not;

    not data_n(data_not, data);
    nand set_gate(set_out, data, clk);
    nand reset_gate(reset_out, data_not, clk);

    wire q_wire, qn_wire;

    nand ng1(q_wire, set_out, qn_wire);
    nand ng2(qn_wire, reset_out, q_wire);

    assign q = q_wire;
    assign q_not = qn_wire;

endmodule

regfile/dff/dff.v
module dff(
    input clk, data,
    output q, q_not
);
    wire l1, nClk;

    not not_clk(nClk, clk);

    d_latch latch1(.q(l1), .data(data), .clk(nClk));
    d_latch latch2(.q(q), .q_not(q_not), .data(l1), .clk(clk));

endmodule

regfile/dff/dff_tb.v
`timescale 1 ns / 100ps
module dff_tb;
    reg data = 1'b0, clk = 1'b0;
    wire q, q_not;

    dff flip_flop(.data(data), .clk(clk), .q(q), .q_not(q_not));

    initial begin 
        #5
        data = 1'b1;
        $display("data:%b, clk:%b => q:%b, q_not:%b", data, clk, q, q_not);
        #5
        clk = 1'b1;
        #5
        data = 1'b0;
        #5
        clk = 1'b0;
        #5
        clk = 1'b1;
        #5
        data = 1'b1;
        #5
        data = 1'b0;
        #2
        clk = 1'b0;
        #3
        data = 1'b1;
        #5
        $finish;
    end

    initial begin
        $dumpfile("dff_tb_wave.vcd");
        $dumpvars(0, dff_tb);
    end
endmodule

regfile/dff/dff_tb_wave.vcd
$date
	Thu Feb 09 17:46:10 2023
$end
$version
	Icarus Verilog
$end
$timescale
	100ps
$end
$scope module dff_tb $end
$var wire 1 ! q_not $end
$var wire 1 " q $end
$var reg 1 # clk $end
$var reg 1 $ data $end
$scope module flip_flop $end
$var wire 1 # clk $end
$var wire 1 $ data $end
$var wire 1 % nClk $end
$var wire 1 ! q_not $end
$var wire 1 " q $end
$var wire 1 & l1 $end
$scope module latch1 $end
$var wire 1 % clk $end
$var wire 1 $ data $end
$var wire 1 ' data_not $end
$var wire 1 & q $end
$var wire 1 ( q_not $end
$var wire 1 ) q_wire $end
$var wire 1 * qn_wire $end
$var wire 1 + reset_out $end
$var wire 1 , set_out $end
$upscope $end
$scope module latch2 $end
$var wire 1 # clk $end
$var wire 1 & data $end
$var wire 1 - data_not $end
$var wire 1 " q $end
$var wire 1 ! q_not $end
$var wire 1 . q_wire $end
$var wire 1 / qn_wire $end
$var wire 1 0 reset_out $end
$var wire 1 1 set_out $end
$upscope $end
$upscope $end
$upscope $end
$enddefinitions $end
$comment Show the parameter values. $end
$dumpall
$end
#0
$dumpvars
11
10
x/
x.
1-
1,
0+
1*
0)
1(
1'
0&
1%
0$
0#
x"
x!
$end
#50
0(
0*
0-
1+
1&
1)
0'
0,
1$
#100
0!
0/
1,
1"
1.
0%
01
1#
#150
1'
0$
#200
1-
0&
0)
1(
1*
0+
1%
11
0#
#250
0"
0.
1+
1!
1/
0%
00
1#
#300
0'
1$
#350
1'
0$
#370
0+
1%
10
0#
#400
0(
0*
0-
1+
1&
1)
0'
0,
1$
