lab1/full_adder.v
module full_adder (
    S, Cout, A, B, Cin
);
    input A, B, Cin;
    output S, Cout;
    wire w1, w2, w3;

    xor s_result(S, A, B, Cin);

    and ab_and(w1, A, B);
    and ac_and(w2, A, Cin);
    and bc_and(w3, B, Cin);

    or c_result(Cout, w1, w2, w3);
endmodule

lab1/two_bit_adder.v
module two_bit_adder (
    S, Cout, A, B, Cin
);

    input [1:0] A, B;
    input Cin;
    output [1:0] S;
    output Cout;
    wire c0;

    full_adder adder0(S[0], c0, A[0], B[0], Cin);
    full_adder adder1(S[1], Cout, A[1], B[1], c0);
    
endmodule

lab1/two_bit_adder_tb.v
`timescale 1 ns / 100ps
module two_bit_adder_tb;
    wire[1:0] A, B;
    wire Cin;
    wire[1:0] S;
    wire Cout;

    two_bit_adder adder(S, Cout, A, B, Cin);
    integer i;

    assign {Cin, A, B} = i[4:0];
    initial begin
        for(i = 0; i < 32; i = i + 1) begin
            #20;
            $display("A:%b, B:%b, Cin:%b => S:%b, Cout:%b", A, B, Cin, S, Cout);
        end
        $finish;
    end

    initial begin
        $dumpfile("two_bit_adder_tb_wave.vcd");
        $dumpvars(0, two_bit_adder_tb);
    end

endmodule

lab1/two_bit_adder_tb_wave.vcd
$date
	Thu Jan 19 17:05:17 2023
$end
$version
	Icarus Verilog
$end
$timescale
	100ps
$end
$scope module two_bit_adder_tb $end
$var wire 2 ! S [1:0] $end
$var wire 1 " Cout $end
$var wire 1 # Cin $end
$var wire 2 $ B [1:0] $end
$var wire 2 % A [1:0] $end
$var integer 32 & i [31:0] $end
$scope module adder $end
$var wire 2 ' A [1:0] $end
$var wire 2 ( B [1:0] $end
$var wire 1 # Cin $end
$var wire 1 ) c0 $end
$var wire 2 * S [1:0] $end
$var wire 1 " Cout $end
$scope module adder0 $end
$var wire 1 + A $end
$var wire 1 , B $end
$var wire 1 # Cin $end
$var wire 1 ) Cout $end
$var wire 1 - S $end
$var wire 1 . w1 $end
$var wire 1 / w2 $end
$var wire 1 0 w3 $end
$upscope $end
$scope module adder1 $end
$var wire 1 1 A $end
$var wire 1 2 B $end
$var wire 1 ) Cin $end
$var wire 1 " Cout $end
$var wire 1 3 S $end
$var wire 1 4 w1 $end
$var wire 1 5 w2 $end
$var wire 1 6 w3 $end
$upscope $end
$upscope $end
$upscope $end
$enddefinitions $end
$comment Show the parameter values. $end
$dumpall
$end
#0
$dumpvars
06
05
04
03
02
01
00
0/
0.
0-
0,
0+
b0 *
0)
b0 (
b0 '
b0 &
b0 %
b0 $
0#
0"
b0 !
$end
#200
b1 !
b1 *
1-
1,
b1 $
b1 (
b1 &
#400
0-
b10 !
b10 *
13
0,
12
b10 $
b10 (
b10 &
#600
b11 !
b11 *
1-
1,
b11 $
b11 (
b11 &
#800
b1 !
b1 *
03
0,
02
1+
b0 $
b0 (
b1 %
b1 '
b100 &
#1000
13
1)
b10 !
b10 *
0-
1.
1,
b1 $
b1 (
b101 &
#1200
0)
0"
1-
0.
b11 !
b11 *
13
06
0,
12
b10 $
b10 (
b110 &
#1400
1"
03
16
1)
b0 !
b0 *
0-
1.
1,
b11 $
b11 (
b111 &
#1600
0"
b10 !
b10 *
13
0)
06
0.
05
0,
02
0+
11
b0 $
b0 (
b10 %
b10 '
b1000 &
#1800
b11 !
b11 *
1-
1,
b1 $
b1 (
b1001 &
#2000
1"
0-
b0 !
b0 *
03
14
0,
12
b10 $
b10 (
b1010 &
#2200
b1 !
b1 *
1-
1,
b11 $
b11 (
b1011 &
#2400
0"
b11 !
b11 *
13
04
0,
02
1+
b0 $
b0 (
b11 %
b11 '
b1100 &
#2600
1"
03
15
1)
b0 !
b0 *
0-
1.
1,
b1 $
b1 (
b1101 &
#2800
05
0)
1-
0.
b1 !
b1 *
03
14
06
0,
12
b10 $
b10 (
b1110 &
#3000
13
15
16
1)
b10 !
b10 *
0-
1.
1,
b11 $
b11 (
b1111 &
#3200
03
0)
0"
06
0.
04
05
0,
02
0+
01
b1 !
b1 *
1-
0/
00
b0 $
b0 (
b0 %
b0 '
1#
b10000 &
#3400
13
1)
b10 !
b10 *
0-
10
1,
b1 $
b1 (
b10001 &
#3600
0)
0"
1-
00
b11 !
b11 *
13
06
0,
12
b10 $
b10 (
b10010 &
#3800
1"
03
16
1)
b0 !
b0 *
0-
10
1,
b11 $
b11 (
b10011 &
#4000
0"
00
b10 !
b10 *
13
06
1/
0,
02
1+
b0 $
b0 (
b1 %
b1 '
b10100 &
#4200
b11 !
b11 *
1-
1.
10
1,
b1 $
b1 (
b10101 &
#4400
1"
0-
0.
00
b0 !
b0 *
03
16
0,
12
b10 $
b10 (
b10110 &
#4600
b1 !
b1 *
1-
1.
10
1,
b11 $
b11 (
b10111 &
#4800
0"
b11 !
b11 *
13
0)
00
06
0.
0/
05
0,
02
0+
11
b0 $
b0 (
b10 %
b10 '
b11000 &
#5000
1"
03
15
1)
b0 !
b0 *
0-
10
1,
b1 $
b1 (
b11001 &
#5200
05
0)
1-
00
b1 !
b1 *
03
14
06
0,
12
b10 $
b10 (
b11010 &
#5400
13
15
16
1)
b10 !
b10 *
0-
10
1,
b11 $
b11 (
b11011 &
#5600
00
b0 !
b0 *
03
04
06
1/
0,
02
1+
b0 $
b0 (
b11 %
b11 '
b11100 &
#5800
b1 !
b1 *
1-
1.
10
1,
b1 $
b1 (
b11101 &
#6000
0-
0.
00
b10 !
b10 *
13
14
16
0,
12
b10 $
b10 (
b11110 &
#6200
b11 !
b11 *
1-
1.
10
1,
b11 $
b11 (
b11111 &
#6400
03
0)
0"
06
0.
04
05
0,
02
0+
01
b0 !
b0 *
0-
0/
00
b0 $
b0 (
b0 %
b0 '
0#
b100000 &
