lab2/full_adder_nand.v
module full_adder_nand (
    S, Cout, A, B, Cin
);
   input A, B, Cin;
   output S, Cout;
   
   wire AB, ABA, ABB, nAB, nABC, nABCC, nABCA;
   nand nandAB(AB, A, B);
   nand nandABA(ABA, AB, A);
   nand nandABB(ABB, AB, B);
   nand nandnAB(nAB, ABA, ABB);

   nand nandnABC(nABC, nAB, Cin);
   nand nandnABCA(nABCA, nABC, nAB);
   nand nandnABCC(nABCC, nABC, Cin);
   nand nandS(S, nABCA, nABCC);
   nand nandCout(Cout, AB, nABC);
endmodule

lab2/full_adder_nand_tb.v
`timescale 1 ns / 100ps
module full_adder_nand_tb;
    reg A, B, Cin;
    wire S, Cout;
    full_adder_nand adder(.A(A), .B(B), .Cin(Cin), .S(S), .Cout(Cout));

    initial begin
        A = 0;
        B = 0;
        Cin = 0;
        #80;
        $finish;
    end

    always #10 A = ~A;
    always #20 B = ~B;
    always #40 Cin = ~Cin;

    always @(A, B, Cin) begin
        #1
        $display("A:%b, B:%b, Cin:%b -> S:%b, Cout:%b", A, B, Cin, S, Cout);
    end

    initial begin
        $dumpfile("test_adder_nand_tb_wave.vcd");
        $dumpvars(0, full_adder_nand_tb);
    end

endmodule

lab2/test_adder_nand_tb_wave.vcd
$date
	Thu Jan 26 15:56:33 2023
$end
$version
	Icarus Verilog
$end
$timescale
	100ps
$end
$scope module full_adder_nand_tb $end
$var wire 1 ! S $end
$var wire 1 " Cout $end
$var reg 1 # A $end
$var reg 1 $ B $end
$var reg 1 % Cin $end
$scope module adder $end
$var wire 1 # A $end
$var wire 1 & AB $end
$var wire 1 ' ABA $end
$var wire 1 ( ABB $end
$var wire 1 $ B $end
$var wire 1 % Cin $end
$var wire 1 " Cout $end
$var wire 1 ! S $end
$var wire 1 ) nAB $end
$var wire 1 * nABC $end
$var wire 1 + nABCA $end
$var wire 1 , nABCC $end
$upscope $end
$upscope $end
$enddefinitions $end
$comment Show the parameter values. $end
$dumpall
$end
#0
$dumpvars
1,
1+
1*
0)
1(
1'
1&
0%
0$
0#
0"
0!
$end
#100
1!
0+
1)
0'
1#
#200
1'
0(
0#
1$
#300
0!
1+
0)
1(
1"
0&
1'
1#
#400
0"
1!
1&
0,
0#
0$
1%
#500
0!
1,
1"
0*
1+
1)
0'
1#
#600
1'
0(
0#
1$
#700
1!
0,
1*
0)
1(
0&
1'
1#
#800
0"
0!
1&
1,
0#
0$
0%
